{
    "asset": {
        "format": "png",
        "id": "260634977f6ee399a982f31b0c19a477",
        "name": "00026.png",
        "path": "file:D:/Adnan/Estudios/Uni/UltimQuatrimestre/PAE/CiudadesDesdeElCielo/CiudadesDesdeElCielo/Images/Images/TrainYourOwnYOLO/Data/Source_Images/Training_Images/00026.png",
        "size": {
            "width": 1920,
            "height": 1080
        },
        "state": 2,
        "type": 1
    },
    "regions": [
        {
            "id": "nGYIV2IyN",
            "type": "RECTANGLE",
            "tags": [
                "Crane"
            ],
            "boundingBox": {
                "height": 320.29411764705884,
                "width": 426.0785665058581,
                "left": 795.2584424534804,
                "top": 582.4770220588235
            },
            "points": [
                {
                    "x": 795.2584424534804,
                    "y": 582.4770220588235
                },
                {
                    "x": 1221.3370089593384,
                    "y": 582.4770220588235
                },
                {
                    "x": 1221.3370089593384,
                    "y": 902.7711397058823
                },
                {
                    "x": 795.2584424534804,
                    "y": 902.7711397058823
                }
            ]
        },
        {
            "id": "b68BZNf-x",
            "type": "RECTANGLE",
            "tags": [
                "Crane"
            ],
            "boundingBox": {
                "height": 571.7647058823529,
                "width": 440.63404548587187,
                "left": 619.2694693314955,
                "top": 164.24172794117646
            },
            "points": [
                {
                    "x": 619.2694693314955,
                    "y": 164.24172794117646
                },
                {
                    "x": 1059.9035148173673,
                    "y": 164.24172794117646
                },
                {
                    "x": 1059.9035148173673,
                    "y": 736.0064338235294
                },
                {
                    "x": 619.2694693314955,
                    "y": 736.0064338235294
                }
            ]
        },
        {
            "id": "GNLB9jP1d",
            "type": "RECTANGLE",
            "tags": [
                "Crane"
            ],
            "boundingBox": {
                "height": 239.55882352941177,
                "width": 464.4521019986217,
                "left": 340.0689179875948,
                "top": 111.30055147058823
            },
            "points": [
                {
                    "x": 340.0689179875948,
                    "y": 111.30055147058823
                },
                {
                    "x": 804.5210199862164,
                    "y": 111.30055147058823
                },
                {
                    "x": 804.5210199862164,
                    "y": 350.859375
                },
                {
                    "x": 340.0689179875948,
                    "y": 350.859375
                }
            ]
        }
    ],
    "version": "2.2.0"
}