{
    "asset": {
        "format": "jpg",
        "id": "43d58f698e69654e3d697794feab8c75",
        "name": "00013.jpg",
        "path": "file:D:/Adnan/Estudios/Uni/UltimQuatrimestre/PAE/CiudadesDesdeElCielo/CiudadesDesdeElCielo/Images/Images/TrainYourOwnYOLO/Data/Source_Images/Training_Images/00013.jpg",
        "size": {
            "width": 1500,
            "height": 1244
        },
        "state": 2,
        "type": 1
    },
    "regions": [
        {
            "id": "1TfhVneHR",
            "type": "RECTANGLE",
            "tags": [
                "Crane"
            ],
            "boundingBox": {
                "height": 721.6277056277056,
                "width": 1500.0000000000002,
                "left": 0,
                "top": 401.20346320346323
            },
            "points": [
                {
                    "x": 0,
                    "y": 401.20346320346323
                },
                {
                    "x": 1500.0000000000002,
                    "y": 401.20346320346323
                },
                {
                    "x": 1500.0000000000002,
                    "y": 1122.831168831169
                },
                {
                    "x": 0,
                    "y": 1122.831168831169
                }
            ]
        }
    ],
    "version": "2.2.0"
}